fpdf/__init__.py
fpdf/actions.py
fpdf/deprecation.py
fpdf/errors.py
fpdf/fonts.py
fpdf/fpdf.py
fpdf/graphics_state.py
fpdf/html.py
fpdf/image_parsing.py
fpdf/outline.py
fpdf/recorder.py
fpdf/structure_tree.py
fpdf/syntax.py
fpdf/template.py
fpdf/transitions.py
fpdf/ttfonts.py
fpdf/util.py
dan123456789-2.4.6.dist-info/LICENSE
dan123456789-2.4.6.dist-info/METADATA
dan123456789-2.4.6.dist-info/WHEEL
dan123456789-2.4.6.dist-info/top_level.txt
dan123456789-2.4.6.dist-info/RECORD
